requests_raw/__init__.py
requests_raw/__version__.py
requests_raw/adapters.py
requests_raw/api.py
requests_raw/connection.py
requests_raw/connectionpool.py
requests_raw/sessions.py
requests_raw/socks.py
requests_raw-2.0.2.dist-info/LICENSE
requests_raw-2.0.2.dist-info/METADATA
requests_raw-2.0.2.dist-info/WHEEL
requests_raw-2.0.2.dist-info/top_level.txt
requests_raw-2.0.2.dist-info/RECORD
