Metadata-Version: 2.1
Name: requests-raw
Version: 2.0.2
Summary: HTTP communication through raw sockets using requests for RFC compliance testing
Home-page: https://github.com/realgam3/requests-raw
Author: Tomer Zait (realgam3)
Author-email: realgam3@gmail.com
License: Apache 2.0
Project-URL: Source, https://github.com/realgam3/requests-raw
Platform: any
Classifier: Development Status :: 5 - Production/Stable
Classifier: Environment :: Web Environment
Classifier: Intended Audience :: Developers
Classifier: Intended Audience :: Science/Research
Classifier: License :: OSI Approved :: Apache Software License
Classifier: Natural Language :: English
Classifier: Operating System :: OS Independent
Classifier: Programming Language :: Python
Classifier: Programming Language :: Python :: 3
Classifier: Programming Language :: Python :: 3.7
Classifier: Programming Language :: Python :: 3.8
Classifier: Programming Language :: Python :: 3.9
Classifier: Programming Language :: Python :: 3.10
Classifier: Programming Language :: Python :: 3.11
Classifier: Programming Language :: Python :: 3.12
Classifier: Programming Language :: Python :: 3 :: Only
Classifier: Programming Language :: Python :: Implementation :: CPython
Classifier: Programming Language :: Python :: Implementation :: PyPy
Requires-Python: >=3.7
Provides-Extra: security
Provides-Extra: socks
Provides-Extra: use_chardet_on_py3
License-File: LICENSE
